google/cloud/dataqna/__init__.py
google/cloud/dataqna/gapic_version.py
google/cloud/dataqna/py.typed
google/cloud/dataqna_v1alpha/__init__.py
google/cloud/dataqna_v1alpha/gapic_metadata.json
google/cloud/dataqna_v1alpha/gapic_version.py
google/cloud/dataqna_v1alpha/py.typed
google/cloud/dataqna_v1alpha/services/__init__.py
google/cloud/dataqna_v1alpha/services/auto_suggestion_service/__init__.py
google/cloud/dataqna_v1alpha/services/auto_suggestion_service/async_client.py
google/cloud/dataqna_v1alpha/services/auto_suggestion_service/client.py
google/cloud/dataqna_v1alpha/services/auto_suggestion_service/transports/__init__.py
google/cloud/dataqna_v1alpha/services/auto_suggestion_service/transports/base.py
google/cloud/dataqna_v1alpha/services/auto_suggestion_service/transports/grpc.py
google/cloud/dataqna_v1alpha/services/auto_suggestion_service/transports/grpc_asyncio.py
google/cloud/dataqna_v1alpha/services/auto_suggestion_service/transports/rest.py
google/cloud/dataqna_v1alpha/services/auto_suggestion_service/transports/rest_base.py
google/cloud/dataqna_v1alpha/services/question_service/__init__.py
google/cloud/dataqna_v1alpha/services/question_service/async_client.py
google/cloud/dataqna_v1alpha/services/question_service/client.py
google/cloud/dataqna_v1alpha/services/question_service/transports/__init__.py
google/cloud/dataqna_v1alpha/services/question_service/transports/base.py
google/cloud/dataqna_v1alpha/services/question_service/transports/grpc.py
google/cloud/dataqna_v1alpha/services/question_service/transports/grpc_asyncio.py
google/cloud/dataqna_v1alpha/services/question_service/transports/rest.py
google/cloud/dataqna_v1alpha/services/question_service/transports/rest_base.py
google/cloud/dataqna_v1alpha/types/__init__.py
google/cloud/dataqna_v1alpha/types/annotated_string.py
google/cloud/dataqna_v1alpha/types/auto_suggestion_service.py
google/cloud/dataqna_v1alpha/types/question.py
google/cloud/dataqna_v1alpha/types/question_service.py
google_cloud_data_qna-0.12.0.dist-info/licenses/LICENSE
google_cloud_data_qna-0.12.0.dist-info/METADATA
google_cloud_data_qna-0.12.0.dist-info/WHEEL
google_cloud_data_qna-0.12.0.dist-info/top_level.txt
google_cloud_data_qna-0.12.0.dist-info/RECORD
